hrvlib/__init__.py
hrvlib/_core.cpython-39-aarch64-linux-gnu.so
hrvlib/_core.pyi
hrvlib/detrend.py
hrvlib/py.typed
hrvlib-0.0.0a1.dist-info/METADATA
hrvlib-0.0.0a1.dist-info/WHEEL
hrvlib-0.0.0a1.dist-info/RECORD
