Metadata-Version: 2.1
Name: hrvlib
Version: 0.0.0a1
Summary: Add your description here
Author-Email: faby <fabian.kropfhamer@gmail.com>
Requires-Python: >=3.9
Requires-Dist: numpy>=2.3.4
Requires-Dist: scipy>=1.16.3
Provides-Extra: test
Requires-Dist: pytest>=8.0.0; extra == "test"
Requires-Dist: pytest-cov>=4.1.0; extra == "test"
